examples/__init__.py
examples/run_DataAugment.py
examples/run_SDialogueGeneration.py
examples/run_SEntityRecognition.py
examples/run_STextClassification.py
examples/run_STextSummarization.py
examples/run_UKeywordsExtract.py
examples/run_USemanticSearch.py
examples/run_UTextEmbedding.py
examples/run_UTextSimilarity.py
unlp/__init__.py
unlp/augment/__init__.py
unlp/augment/config.py
unlp/augment/data_augmentation.py
unlp/augment/eda/__init__.py
unlp/augment/eda/eda.py
unlp/augment/eda/synonym_replace.py
unlp/augment/translate/__init__.py
unlp/augment/translate/baidu_translate.py
unlp/supervised/__init__.py
unlp/supervised/dialogue_generation.py
unlp/supervised/sequence_labeling.py
unlp/supervised/text_classify.py
unlp/supervised/text_summarize.py
unlp/supervised/classification/__init__.py
unlp/supervised/classification/evaluate.py
unlp/supervised/classification/predict.py
unlp/supervised/classification/run.py
unlp/supervised/classification/train.py
unlp/supervised/classification/data/__init__.py
unlp/supervised/classification/data/THUCNews/__init__.py
unlp/supervised/classification/data/THUCNews/data/__init__.py
unlp/supervised/classification/data/THUCNews/data/class.txt
unlp/supervised/classification/data/THUCNews/data/dev.txt
unlp/supervised/classification/data/THUCNews/data/test.txt
unlp/supervised/classification/data/THUCNews/data/train.txt
unlp/supervised/classification/models/DPCNN.py
unlp/supervised/classification/models/FastText.py
unlp/supervised/classification/models/TextCNN.py
unlp/supervised/classification/models/TextRCNN.py
unlp/supervised/classification/models/TextRNN.py
unlp/supervised/classification/models/TextRNN_Att.py
unlp/supervised/classification/models/__init__.py
unlp/supervised/classification/models/transformer/BERT.py
unlp/supervised/classification/models/transformer/ERNIE.py
unlp/supervised/classification/models/transformer/__init__.py
unlp/supervised/classification/models/transformer/bert_modeling.py
unlp-1.4.6.dist-info/LICENSE
unlp-1.4.6.dist-info/METADATA
unlp-1.4.6.dist-info/WHEEL
unlp-1.4.6.dist-info/top_level.txt
unlp-1.4.6.dist-info/RECORD
