Metadata-Version: 2.1
Name: unlp
Version: 1.4.6
Summary: a library that get text embeddings
Home-page: https://github.com/Hanscal/unlp
Author: hanscal
Author-email: hanscalcai@163.com, unagi_jason@163.com
License: UNKNOWN
Platform: UNKNOWN
Classifier: Programming Language :: Python :: 3.6
Classifier: Programming Language :: Python :: 3.7
Classifier: License :: OSI Approved :: MIT License
Classifier: Operating System :: OS Independent
License-File: LICENSE
